rust_py_tools_d-0.1.4.dist-info/METADATA
rust_py_tools_d-0.1.4.dist-info/WHEEL
rust_py_tools_d-0.1.4.dist-info/license_files/LICENSE
rust_py_tools_d/py.typed
rust_py_tools_d/string.pyi
rust_py_tools_d/__init__.py
rust_py_tools_d/rust_py_tools_d.cp39-win_amd64.pyd
rust_py_tools_d-0.1.4.dist-info/RECORD
