Metadata-Version: 2.1
Name: rust-py-tools-d
Version: 0.1.4
Classifier: Programming Language :: Rust
Classifier: Programming Language :: Python :: Implementation :: CPython
Classifier: Operating System :: MacOS
Classifier: Operating System :: Microsoft :: Windows
Classifier: Operating System :: POSIX :: Linux
Classifier: Programming Language :: Rust
Classifier: Programming Language :: Python :: 3.7
Classifier: Programming Language :: Python :: 3.8
Classifier: Programming Language :: Python :: 3.9
Classifier: Programming Language :: Python :: 3.10
Classifier: Programming Language :: Python :: 3.11
Requires-Dist: typing_extensions; python_version < "3.11.0"
License-File: LICENSE
Author: dandan <454273687@qq.com>
Author-email: Dan dan <454273687@qq.com>
Requires-Python: >=3.7
Project-URL: Homepage, https://github.com/wjshan/rust-py-tools
Project-URL: Source, https://github.com/wjshan/rust-py-tools
